PdfFieldFiller/__init__.py
PdfFieldFiller/_version.py
PdfFieldFiller/read_form.py
PdfFieldFiller/utils.py
PdfFieldFiller/write_form.py
PdfFieldFiller-1.0.0.dist-info/LICENSE
PdfFieldFiller-1.0.0.dist-info/METADATA
PdfFieldFiller-1.0.0.dist-info/WHEEL
PdfFieldFiller-1.0.0.dist-info/top_level.txt
PdfFieldFiller-1.0.0.dist-info/RECORD
